{
  "week": "2026-W21",
  "period": "2026-05-18 → 2026-05-24",
  "stats": { "prs": 35, "linesAdded": 50279, "linesRemoved": 13852, "hotfixes": 20 },
  "chart": { "bugCount": 33, "featCount": 1, "enhCount": 1 },
  "priorityChart": { "critCount": 20, "highCount": 0, "normCount": 15, "lowCount": 0 },
  "prs": [
    { "title": "Campaign Approval for PCL", "url": "https://github.com/MediaJel/mediajel-dashboard/pull/11346", "category": "bug", "priority": "critical", "linesAdded": 1, "linesRemoved": 1 },
    { "title": "Add sync modes across data-factory v1 + v2 UIs with adapter-managed defaults", "url": "https://github.com/MediaJel/amplication-nestjs-microservices/pull/2076", "category": "feature", "priority": "normal", "linesAdded": 2309, "linesRemoved": 132 },
    { "title": "Remove Statara Partitions job", "url": "https://github.com/MediaJel/amplication-nestjs-microservices/pull/2203", "category": "bug", "priority": "critical", "linesAdded": 0, "linesRemoved": 102 },
    { "title": "Add new internal service env to production", "url": "https://github.com/MediaJel/amplication-nestjs-microservices/pull/2204", "category": "bug", "priority": "critical", "linesAdded": 11, "linesRemoved": 1 },
    { "title": "Campaign Requestor Enhancements and Line Item Management", "url": "https://github.com/MediaJel/mediajel-dashboard/pull/11352", "category": "bug", "priority": "normal", "linesAdded": 2005, "linesRemoved": 370 },
    { "title": "Add type field to all campaign order report queries for Demo Campaign", "url": "https://github.com/MediaJel/mediajel-dashboard/pull/11340", "category": "bug", "priority": "critical", "linesAdded": 8, "linesRemoved": 0 },
    { "title": "Demo Campaign", "url": "https://github.com/MediaJel/mediajel-gql-service/pull/7481", "category": "bug", "priority": "critical", "linesAdded": 4, "linesRemoved": 4 },
    { "title": "Nexxen Integration Fixes and Data Factory Cleanup", "url": "https://github.com/MediaJel/amplication-nestjs-microservices/pull/2211", "category": "bug", "priority": "normal", "linesAdded": 7, "linesRemoved": 87 },
    { "title": "Remove Audience Type dropdown from Demograph reach panel", "url": "https://github.com/MediaJel/mediajel-dashboard/pull/11322", "category": "bug", "priority": "critical", "linesAdded": 10, "linesRemoved": 48 },
    { "title": "Removed Salesforce Rate-Limit", "url": "https://github.com/MediaJel/mediajel-gql-service/pull/7485", "category": "bug", "priority": "critical", "linesAdded": 7, "linesRemoved": 7 },
    { "title": "NexxenCredentialForwardFix", "url": "https://github.com/MediaJel/amplication-nestjs-microservices/pull/2218", "category": "bug", "priority": "normal", "linesAdded": 23, "linesRemoved": 41 },
    { "title": "Salesforce Additional Fields in PCL", "url": "https://github.com/MediaJel/mediajel-gql-service/pull/7489", "category": "bug", "priority": "critical", "linesAdded": 8, "linesRemoved": 0 },
    { "title": "Revert \"[HOTFIX] Salesforce Additional Fields in PCL\"", "url": "https://github.com/MediaJel/mediajel-gql-service/pull/7493", "category": "enhancement", "priority": "critical", "linesAdded": 0, "linesRemoved": 8 },
    { "title": "Fix reprocess button not process on cluster", "url": "https://github.com/MediaJel/mediajel-gql-service/pull/7494", "category": "bug", "priority": "critical", "linesAdded": 17, "linesRemoved": 2 },
    { "title": "For reprocess button remove the prisma1 query", "url": "https://github.com/MediaJel/mediajel-gql-service/pull/7495", "category": "bug", "priority": "critical", "linesAdded": 19, "linesRemoved": 100 },
    { "title": "Added Salesforce Fields and CPM", "url": "https://github.com/MediaJel/mediajel-dashboard/pull/11353", "category": "bug", "priority": "critical", "linesAdded": 218, "linesRemoved": 48 },
    { "title": "Salesforce Additional Fields in PCL (re-apply + new fields)", "url": "https://github.com/MediaJel/mediajel-gql-service/pull/7500", "category": "bug", "priority": "critical", "linesAdded": 9, "linesRemoved": 0 },
    { "title": "Removed Console Log", "url": "https://github.com/MediaJel/mediajel-dashboard/pull/11359", "category": "bug", "priority": "critical", "linesAdded": 0, "linesRemoved": 2 },
    { "title": "Multiple Transactions Fix", "url": "https://github.com/MediaJel/mediajel-dashboard/pull/11358", "category": "bug", "priority": "normal", "linesAdded": 16, "linesRemoved": 7 },
    { "title": "Page flickers after clicking task link", "url": "https://github.com/MediaJel/mediajel-dashboard/pull/11332", "category": "bug", "priority": "critical", "linesAdded": 426, "linesRemoved": 29 },
    { "title": "Guard xAxis access when Google data is empty", "url": "https://github.com/MediaJel/mediajel-dashboard/pull/11362", "category": "bug", "priority": "normal", "linesAdded": 127, "linesRemoved": 12 },
    { "title": "Paid Search Missing Dates", "url": "https://github.com/MediaJel/mediajel-gql-service/pull/7504", "category": "bug", "priority": "normal", "linesAdded": 44, "linesRemoved": 19 },
    { "title": "Enhancement of Task Comment Full Details", "url": "https://github.com/MediaJel/mediajel-dashboard/pull/11308", "category": "bug", "priority": "normal", "linesAdded": 1393, "linesRemoved": 23 },
    { "title": "Prevent 401 on first load of Widget Dev page", "url": "https://github.com/MediaJel/amplication-nestjs-microservices/pull/2199", "category": "bug", "priority": "critical", "linesAdded": 570, "linesRemoved": 5 },
    { "title": "Unblock Ingest button for fixed-template adapters", "url": "https://github.com/MediaJel/amplication-nestjs-microservices/pull/2229", "category": "bug", "priority": "critical", "linesAdded": 635, "linesRemoved": 22 },
    { "title": "Pin Google Maps API to v3.64 to restore HeatmapLayer", "url": "https://github.com/MediaJel/mediajel-dashboard/pull/11378", "category": "bug", "priority": "critical", "linesAdded": 1, "linesRemoved": 1 },
    { "title": "Campaign Details phase-2 facelift + v2 scaffold + 10 shared primitives", "url": "https://github.com/MediaJel/mediajel-dashboard/pull/11159", "category": "bug", "priority": "normal", "linesAdded": 36173, "linesRemoved": 12484 },
    { "title": "Stop ingestion scheduler infinite loop", "url": "https://github.com/MediaJel/amplication-nestjs-microservices/pull/2232", "category": "bug", "priority": "normal", "linesAdded": 666, "linesRemoved": 51 },
    { "title": "Task Management Form Request", "url": "https://github.com/MediaJel/mediajel-gql-service/pull/7505", "category": "bug", "priority": "normal", "linesAdded": 1, "linesRemoved": 0 },
    { "title": "Fix publish pipeline - address out-of-memory, resume from remaining chunk to be upload", "url": "https://github.com/MediaJel/amplication-nestjs-microservices/pull/2189", "category": "bug", "priority": "critical", "linesAdded": 5453, "linesRemoved": 169 },
    { "title": "Scope Verify Domain validation to tagDomain field only (MED-92)", "url": "https://github.com/MediaJel/mediajel-dashboard/pull/11393", "category": "bug", "priority": "normal", "linesAdded": 1, "linesRemoved": 1 },
    { "title": "Restructure task management route to avoid flickering", "url": "https://github.com/MediaJel/mediajel-dashboard/pull/11395", "category": "bug", "priority": "critical", "linesAdded": 17, "linesRemoved": 9 },
    { "title": "Paid-search-prisma6 crashes: empty campaigns and Decimal aggregation", "url": "https://github.com/MediaJel/mediajel-gql-service/pull/7516", "category": "bug", "priority": "normal", "linesAdded": 35, "linesRemoved": 11 },
    { "title": "Preserve form fields when selecting a Google Places suggestion", "url": "https://github.com/MediaJel/mediajel-dashboard/pull/11365", "category": "bug", "priority": "normal", "linesAdded": 3, "linesRemoved": 7 },
    { "title": "Resolve stale parentState race on create + update in both Controllers", "url": "https://github.com/MediaJel/mediajel-dashboard/pull/11366", "category": "bug", "priority": "normal", "linesAdded": 62, "linesRemoved": 49 }
  ],
  "contributors": [
    { "name": "JC-DMZ22", "url": "https://github.com/JC-DMZ22", "prs": 6, "critical": 0, "high": 0, "normal": 0, "low": 0, "linesAdded": 243, "linesRemoved": 58 },
    { "name": "verdelmediajel", "url": "https://github.com/verdelmediajel", "prs": 6, "critical": 0, "high": 0, "normal": 0, "low": 0, "linesAdded": 9643, "linesRemoved": 427 },
    { "name": "johnjoseph28", "url": "https://github.com/johnjoseph28", "prs": 5, "critical": 0, "high": 0, "normal": 0, "low": 0, "linesAdded": 47, "linesRemoved": 213 },
    { "name": "Russell0813", "url": "https://github.com/Russell0813", "prs": 4, "critical": 0, "high": 0, "normal": 0, "low": 0, "linesAdded": 36239, "linesRemoved": 12541 },
    { "name": "icarlofer", "url": "https://github.com/icarlofer", "prs": 4, "critical": 0, "high": 0, "normal": 0, "low": 0, "linesAdded": 222, "linesRemoved": 49 },
    { "name": "ramzell", "url": "https://github.com/ramzell", "prs": 4, "critical": 0, "high": 0, "normal": 0, "low": 0, "linesAdded": 1837, "linesRemoved": 61 },
    { "name": "bertwin-mediajel", "url": "https://github.com/bertwin-mediajel", "prs": 2, "critical": 0, "high": 0, "normal": 0, "low": 0, "linesAdded": 2012, "linesRemoved": 457 },
    { "name": "rmm03", "url": "https://github.com/rmm03", "prs": 2, "critical": 0, "high": 0, "normal": 0, "low": 0, "linesAdded": 12, "linesRemoved": 4 },
    { "name": "ZeeLiger", "url": "https://github.com/ZeeLiger", "prs": 1, "critical": 0, "high": 0, "normal": 0, "low": 0, "linesAdded": 23, "linesRemoved": 41 },
    { "name": "pacholoamit", "url": "https://github.com/pacholoamit", "prs": 1, "critical": 0, "high": 0, "normal": 0, "low": 0, "linesAdded": 1, "linesRemoved": 1 }
  ],
  "metrics": {
    "mostActiveRepo": "mediajel-dashboard",
    "avgPrSize": 1832,
    "revertCount": 1,
    "prVelocity": 5.0
  }
}
